mustache/__init__.py
mustache/__main__.py
mustache/_version.py
mustache/diff_mustache.py
mustache/mustache.py
mustache_hic-1.3.3.dist-info/LICENSE.txt
mustache_hic-1.3.3.dist-info/METADATA
mustache_hic-1.3.3.dist-info/WHEEL
mustache_hic-1.3.3.dist-info/entry_points.txt
mustache_hic-1.3.3.dist-info/top_level.txt
mustache_hic-1.3.3.dist-info/RECORD
