Metadata-Version: 2.1
Name: mustache-hic
Version: 1.3.3
Summary: Mustache is a Hi-C analysis tool
Home-page: http://github.com/ay-lab/mustache/
Author: Ferhat Ay
Author-email: ferhatay@lji.org
License: MIT
Platform: UNKNOWN
Classifier: Programming Language :: Python :: 3
Classifier: License :: OSI Approved :: MIT License
Classifier: Operating System :: OS Independent
Requires-Python: >=3.5
License-File: LICENSE.txt
Requires-Dist: cooler
Requires-Dist: hic-straw
Requires-Dist: numpy
Requires-Dist: requests
Requires-Dist: scipy
Requires-Dist: pandas
Requires-Dist: statsmodels
Requires-Dist: pathlib
